labrea_type_validation/__init__.py
labrea_type_validation/_runtime.py
labrea_type_validation/_startup.py
labrea_type_validation/_validate.py
labrea_type_validation/_version.py
labrea_type_validation-0.0.1.dist-info/METADATA
labrea_type_validation-0.0.1.dist-info/WHEEL
labrea_type_validation-0.0.1.dist-info/licenses/LICENSE
labrea_type_validation-0.0.1.dist-info/RECORD
